pyrsnapshot/__init__.py
pyrsnapshot/__main__.py
pyrsnapshot/remote.py
pyrsnapshot-0.2.3.dist-info/DESCRIPTION.rst
pyrsnapshot-0.2.3.dist-info/METADATA
pyrsnapshot-0.2.3.dist-info/RECORD
pyrsnapshot-0.2.3.dist-info/WHEEL
pyrsnapshot-0.2.3.dist-info/entry_points.txt
pyrsnapshot-0.2.3.dist-info/metadata.json
pyrsnapshot-0.2.3.dist-info/top_level.txt
